{
  "executadoEm": "2026-06-25T14:43:21.987Z",
  "totalProdutos": 11,
  "relatorio": [
    {
      "id": 2,
      "nome": "Calça Jeans Wide Leg Feminina Cintura Alta Sem Lycra Stillge",
      "status": "atualizado",
      "mudancas": [
        {
          "campo": "precoPor",
          "de": "R$ 54,86",
          "para": "R$ 58,10"
        },
        {
          "campo": "desconto",
          "de": "50% OFF no Pix",
          "para": "47% OFF"
        }
      ]
    },
    {
      "id": 4,
      "nome": "Sofá Retrátil Reclinável 3 Lugares C Molas 1,80m Vegas Suede Cor Preto",
      "status": "atualizado",
      "mudancas": [
        {
          "campo": "precoPor",
          "de": "R$ 999,90",
          "para": "R$ 949,90"
        },
        {
          "campo": "desconto",
          "de": "37% OFF",
          "para": "40% OFF no Pix"
        }
      ]
    }
  ]
}